{
  "": "",
  "?": "",
  "About Page": "",
  "About us": "",
  "Age": "",
  "Age is not correct": "",
  "Article_Error": "",
  "Articles": "",
  "Articles_Not_Found": "",
  "Avatar": "",
  "Cancel": "",
  "City": "",
  "City is necessary": "",
  "Country": "",
  "Currency": "",
  "Details": "",
  "Easy": "",
  "Edit": "",
  "Error while loading the profile": "",
  "Home": "",
  "Home Page": "",
  "Login": "",
  "Login form": "",
  "Logout": "",
  "Name and Last Name are necessary": "",
  "No data": "",
  "NoData": "",
  "Page Not Found": "",
  "Profile": "",
  "Profile Page": "",
  "ProfileTextError": "",
  "ProfileTitleError": "",
  "Reload": "",
  "Save": "",
  "Server error while updating profile": "",
  "ServerError": "",
  "Some Text": "",
  "The article is not found": "",
  "Toggle": "",
  "Try to refresh the page": "",
  "Unexpected mistake occurred": "",
  "Username": "",
  "Username or password is not correct": "",
  "ValidateAge": "",
  "ValidateCity": "",
  "ValidateName": "",
  "Your age": "",
  "Your city": "",
  "Your first name": "",
  "Your last name": "",
  "Your name": "",
  "decrement": "",
  "increment": "",
  "language": "",
  "password": "",
  "username": "",
  "Войти": "",
  "Выйти": ""
}
